rugged/__init__.py
rugged/middleware.py
rugged/py.typed
rugged/unflatteners.py
rugged-0.2.2.dist-info/METADATA
rugged-0.2.2.dist-info/WHEEL
rugged-0.2.2.dist-info/licenses/LICENSE.md
rugged-0.2.2.dist-info/RECORD
