Metadata-Version: 2.1
Name: rugged
Version: 0.2.2
Summary: ASGI middleware to unflatten JSON request bodies
Project-URL: Homepage, https://github.com/rmasters/rugged
Project-URL: Issues, https://github.com/rmasters/rugged/issues
Author-email: Ross Masters <ross@rossmasters.com>
License-File: LICENSE.md
Classifier: Development Status :: 3 - Alpha
Classifier: Framework :: FastAPI
Classifier: Intended Audience :: Developers
Classifier: License :: OSI Approved :: MIT License
Classifier: Operating System :: OS Independent
Classifier: Programming Language :: Python :: 3
Classifier: Programming Language :: Python :: 3 :: Only
Classifier: Programming Language :: Python :: 3.10
Classifier: Programming Language :: Python :: 3.11
Classifier: Programming Language :: Python :: 3.12
Classifier: Programming Language :: Python :: 3.13
Classifier: Topic :: Internet :: WWW/HTTP
Classifier: Topic :: Internet :: WWW/HTTP :: WSGI :: Middleware
Classifier: Typing :: Typed
Requires-Python: >=3.10
Requires-Dist: starlette<=1
